ambivo_mcp_server/__init__.py
ambivo_mcp_server/__main__.py
ambivo_mcp_server/config.py
ambivo_mcp_server/security.py
ambivo_mcp_server/server.py
ambivo_mcp_server-1.0.6.dist-info/licenses/LICENSE
ambivo_mcp_server-1.0.6.dist-info/METADATA
ambivo_mcp_server-1.0.6.dist-info/WHEEL
ambivo_mcp_server-1.0.6.dist-info/entry_points.txt
ambivo_mcp_server-1.0.6.dist-info/top_level.txt
ambivo_mcp_server-1.0.6.dist-info/RECORD
