Metadata-Version: 2.4
Name: ambivo-mcp-server
Version: 1.0.6
Summary: MCP Server for Ambivo API endpoints - Natural language queries and direct entity data access
Home-page: https://github.com/ambivo-corp/ambivo-mcp-server
Author: Ambivo Development Team
Author-email: Ambivo Development Team <dev@ambivo.com>
License: MIT
Project-URL: Homepage, https://github.com/ambivo-corp/ambivo-mcp-server
Project-URL: Bug Tracker, https://github.com/ambivo-corp/ambivo-mcp-server/issues
Project-URL: Documentation, https://github.com/ambivo-corp/ambivo-mcp-server#readme
Project-URL: Source Code, https://github.com/ambivo-corp/ambivo-mcp-server
Keywords: mcp,server,ambivo,api,natural,language,query,entity,data,crm,claude
Classifier: Development Status :: 4 - Beta
Classifier: Intended Audience :: Developers
Classifier: License :: OSI Approved :: MIT License
Classifier: Operating System :: OS Independent
Classifier: Programming Language :: Python :: 3
Classifier: Programming Language :: Python :: 3.11
Classifier: Programming Language :: Python :: 3.12
Classifier: Topic :: Software Development :: Libraries :: Python Modules
Classifier: Topic :: Internet :: WWW/HTTP :: HTTP Servers
Classifier: Topic :: Communications :: Chat
Classifier: Framework :: AsyncIO
Requires-Python: >=3.11
License-File: LICENSE
Requires-Dist: mcp>=1.0.0
Requires-Dist: httpx>=0.25.0
Requires-Dist: pyyaml>=6.0.0
Provides-Extra: dev
Requires-Dist: pytest>=7.0.0; extra == "dev"
Requires-Dist: pytest-asyncio>=0.21.0; extra == "dev"
Requires-Dist: black>=22.0.0; extra == "dev"
Requires-Dist: isort>=5.0.0; extra == "dev"
Provides-Extra: test
Requires-Dist: pytest>=7.0.0; extra == "test"
Requires-Dist: pytest-asyncio>=0.21.0; extra == "test"
Requires-Dist: httpx[test]>=0.25.0; extra == "test"
Dynamic: author
Dynamic: home-page
Dynamic: license-file
Dynamic: requires-python
